README.md
setup.cfg
setup.py
chebxroots/__init__.py
chebxroots/chebcoeffs.py
chebxroots/chebxroots.py
chebxroots/clenshaw.py
chebxroots/convert_to_powers.py
chebxroots/degree_doubling.py
chebxroots/prefs.py
chebxroots/visualization.py
chebxroots.egg-info/PKG-INFO
chebxroots.egg-info/SOURCES.txt
chebxroots.egg-info/dependency_links.txt
chebxroots.egg-info/requires.txt
chebxroots.egg-info/top_level.txt